stocktrader/__init__.py
stocktrader/api.py
traderhelper-0.0.1.dist-info/LICENSE
traderhelper-0.0.1.dist-info/METADATA
traderhelper-0.0.1.dist-info/WHEEL
traderhelper-0.0.1.dist-info/top_level.txt
traderhelper-0.0.1.dist-info/RECORD
