Metadata-Version: 2.1
Name: traderhelper
Version: 0.0.1
Summary: make trader easy
Home-page: UNKNOWN
Author: traderhelper
Author-email: traderhelper@163.com
License: UNKNOWN
Platform: UNKNOWN
Classifier: Programming Language :: Python :: 3
Classifier: License :: OSI Approved :: Apache Software License
Classifier: Operating System :: OS Independent
Requires-Python: >=3.6
Requires-Dist: numpy
Requires-Dist: pandas (>=0.24.0)
